VayDiff/BasicMath.py
VayDiff/VayDiff.py
VayDiff/__init__.py
VayDiff/tests/__init__.py
VayDiff/tests/tests.py
VayDiff/tests/tests_jacobian.py
VayDiff/tests/tests_sec_der.py
VayDiff/tests/tests_vector.py
VayDiff-0.0.3.dist-info/LICENSE
VayDiff-0.0.3.dist-info/METADATA
VayDiff-0.0.3.dist-info/WHEEL
VayDiff-0.0.3.dist-info/top_level.txt
VayDiff-0.0.3.dist-info/RECORD
