Metadata-Version: 2.1
Name: VayDiff
Version: 0.0.3
Summary: Python package for Automatic Differentiation
Home-page: https://github.com/cs207-group-11/cs207-FinalProject
Author: Abhimanyu Vasishth, Zheyu Wu, Yiming Xu
Author-email: 
License: MIT
Keywords: Python,Automatic differentiation
Platform: UNKNOWN
Classifier: Programming Language :: Python :: 3
Classifier: License :: OSI Approved :: MIT License
